probirka/__init__.py
probirka/_aiohttp.py
probirka/_fastapi.py
probirka/_probes.py
probirka/_probirka.py
probirka/_results.py
probirka-0.4.1.dist-info/METADATA
probirka-0.4.1.dist-info/WHEEL
probirka-0.4.1.dist-info/licenses/LICENSE
probirka-0.4.1.dist-info/RECORD
