Metadata-Version: 2.4
Name: probirka
Version: 0.4.1
Summary: Python 3 library to write simple asynchronous health checks (probes)
Project-URL: Repository, https://github.com/appKODE/probirka
Author-email: KODE <slurm@kode.ru>
License-Expression: MIT
License-File: LICENSE
Keywords: health-check,monitoring,probes
Classifier: Development Status :: 5 - Production/Stable
Classifier: Programming Language :: Python :: 3 :: Only
Classifier: Programming Language :: Python :: 3.8
Classifier: Programming Language :: Python :: 3.9
Classifier: Programming Language :: Python :: 3.10
Classifier: Programming Language :: Python :: 3.11
Classifier: Programming Language :: Python :: 3.12
Classifier: Programming Language :: Python :: 3.13
Classifier: Topic :: Software Development :: Libraries :: Python Modules
Requires-Python: >=3.8
